{
  "used_read_access_memory_in_bytes": [
    8422182912,
    8422133760,
    8421289984,
    8421740544,
    8421654528,
    8421855232,
    8421109760,
    8422088704,
    8422379520,
    8390299648,
    8396750848,
    8396935168,
    8396615680
  ],
  "utilization_of_cpu": [
    12.5,
    26.6,
    19.6,
    17.2,
    12.5,
    17.2,
    12.5,
    14.1,
    12.1,
    14.1,
    17.2,
    13.0,
    14.3
  ],
  "used_read_access_memory_in_percentage": [
    49.5,
    49.5,
    49.5,
    49.5,
    49.5,
    49.5,
    49.5,
    49.5,
    49.5,
    49.4,
    49.4,
    49.4,
    49.4
  ],
  "time_duration_with_cpu_profiler_in_sec": 13.4310017,
  "used_algorithm": "ant_colony_tsp_scikit_opt",
  "name_of_src_file": "TSP_CITIES_SET_60_N_6.json"
}