{
  "cities": [
    {
      "number_of_city": 0,
      "x": 0,
      "y": 0
    },
    {
      "number_of_city": 1,
      "x": 287,
      "y": -449
    },
    {
      "number_of_city": 2,
      "x": -66,
      "y": -615
    },
    {
      "number_of_city": 3,
      "x": -978,
      "y": -257
    },
    {
      "number_of_city": 4,
      "x": -898,
      "y": 998
    },
    {
      "number_of_city": 5,
      "x": -299,
      "y": -700
    },
    {
      "number_of_city": 6,
      "x": 920,
      "y": 235
    },
    {
      "number_of_city": 7,
      "x": 232,
      "y": -717
    },
    {
      "number_of_city": 8,
      "x": 456,
      "y": 726
    },
    {
      "number_of_city": 9,
      "x": 201,
      "y": 784
    },
    {
      "number_of_city": 10,
      "x": 953,
      "y": -224
    },
    {
      "number_of_city": 11,
      "x": -617,
      "y": -133
    },
    {
      "number_of_city": 12,
      "x": 382,
      "y": -839
    },
    {
      "number_of_city": 13,
      "x": 446,
      "y": 425
    },
    {
      "number_of_city": 14,
      "x": 412,
      "y": 825
    },
    {
      "number_of_city": 15,
      "x": 953,
      "y": -262
    },
    {
      "number_of_city": 16,
      "x": -89,
      "y": 840
    },
    {
      "number_of_city": 17,
      "x": 614,
      "y": -946
    },
    {
      "number_of_city": 18,
      "x": -334,
      "y": -653
    },
    {
      "number_of_city": 19,
      "x": 803,
      "y": -98
    },
    {
      "number_of_city": 20,
      "x": 667,
      "y": -249
    },
    {
      "number_of_city": 21,
      "x": -332,
      "y": 132
    },
    {
      "number_of_city": 22,
      "x": -239,
      "y": 342
    },
    {
      "number_of_city": 23,
      "x": 853,
      "y": 655
    },
    {
      "number_of_city": 24,
      "x": 323,
      "y": -823
    }
  ],
  "distance_matrix": {
    "0": {
      "24": 884.1142460112268
    },
    "1": {
      "24": 375.7286254732264
    },
    "2": {
      "24": 441.1178980726128
    },
    "3": {
      "24": 1418.7871581037093
    },
    "4": {
      "24": 2192.4602618975787
    },
    "5": {
      "24": 634.0449510878547
    },
    "6": {
      "24": 1214.8139775290701
    },
    "7": {
      "24": 139.70325694127536
    },
    "8": {
      "24": 1554.699327844455
    },
    "9": {
      "24": 1611.624335879798
    },
    "10": {
      "24": 869.3106464319875
    },
    "11": {
      "24": 1166.0617479361888
    },
    "12": {
      "24": 61.1310068623117
    },
    "13": {
      "24": 1254.0466498499966
    },
    "14": {
      "24": 1650.4014663105459
    },
    "15": {
      "24": 843.5763154569953
    },
    "16": {
      "24": 1713.2755178312682
    },
    "17": {
      "24": 315.9272068056184
    },
    "18": {
      "24": 678.6376057956116
    },
    "19": {
      "24": 869.4969810183356
    },
    "20": {
      "24": 669.1875671289777
    },
    "21": {
      "24": 1158.0371323925672
    },
    "22": {
      "24": 1293.471685039916
    },
    "23": {
      "24": 1570.1541325615137
    },
    "24": {
      "24": 0.0
    }
  },
  "stats": {
    "x": {
      "min": -978,
      "avg": 186.0,
      "stdev": 559.7551548072901,
      "median": 287.0,
      "q1": -239.0,
      "q3": 614.0,
      "max": 953
    },
    "y": {
      "min": -946,
      "avg": -40.12,
      "stdev": 607.0295379962988,
      "median": -133.0,
      "q1": -615.0,
      "q3": 425.0,
      "max": 998
    }
  }
}