{
  "cities": [
    {
      "number_of_city": 0,
      "x": 0,
      "y": 0
    },
    {
      "number_of_city": 1,
      "x": 15,
      "y": 189
    },
    {
      "number_of_city": 2,
      "x": 738,
      "y": 141
    },
    {
      "number_of_city": 3,
      "x": -607,
      "y": 16
    },
    {
      "number_of_city": 4,
      "x": -988,
      "y": -844
    },
    {
      "number_of_city": 5,
      "x": -993,
      "y": 94
    },
    {
      "number_of_city": 6,
      "x": 243,
      "y": -447
    },
    {
      "number_of_city": 7,
      "x": 420,
      "y": 875
    },
    {
      "number_of_city": 8,
      "x": 933,
      "y": 138
    },
    {
      "number_of_city": 9,
      "x": 728,
      "y": 489
    },
    {
      "number_of_city": 10,
      "x": 978,
      "y": 849
    },
    {
      "number_of_city": 11,
      "x": 592,
      "y": 444
    },
    {
      "number_of_city": 12,
      "x": 752,
      "y": -817
    },
    {
      "number_of_city": 13,
      "x": -197,
      "y": 186
    },
    {
      "number_of_city": 14,
      "x": 230,
      "y": -178
    },
    {
      "number_of_city": 15,
      "x": -858,
      "y": -617
    },
    {
      "number_of_city": 16,
      "x": -2,
      "y": 196
    },
    {
      "number_of_city": 17,
      "x": 698,
      "y": -15
    },
    {
      "number_of_city": 18,
      "x": -182,
      "y": -825
    },
    {
      "number_of_city": 19,
      "x": -648,
      "y": -433
    },
    {
      "number_of_city": 20,
      "x": 872,
      "y": 901
    },
    {
      "number_of_city": 21,
      "x": -351,
      "y": -964
    },
    {
      "number_of_city": 22,
      "x": -36,
      "y": -104
    },
    {
      "number_of_city": 23,
      "x": 881,
      "y": 944
    },
    {
      "number_of_city": 24,
      "x": 264,
      "y": 766
    },
    {
      "number_of_city": 25,
      "x": -939,
      "y": 48
    },
    {
      "number_of_city": 26,
      "x": 50,
      "y": 474
    },
    {
      "number_of_city": 27,
      "x": 326,
      "y": -776
    },
    {
      "number_of_city": 28,
      "x": 847,
      "y": 681
    },
    {
      "number_of_city": 29,
      "x": -67,
      "y": 566
    },
    {
      "number_of_city": 30,
      "x": 617,
      "y": -518
    },
    {
      "number_of_city": 31,
      "x": 355,
      "y": 647
    },
    {
      "number_of_city": 32,
      "x": -39,
      "y": 995
    },
    {
      "number_of_city": 33,
      "x": -30,
      "y": 649
    },
    {
      "number_of_city": 34,
      "x": 188,
      "y": -694
    },
    {
      "number_of_city": 35,
      "x": 194,
      "y": 506
    },
    {
      "number_of_city": 36,
      "x": 495,
      "y": 246
    },
    {
      "number_of_city": 37,
      "x": -562,
      "y": 888
    },
    {
      "number_of_city": 38,
      "x": 298,
      "y": -365
    },
    {
      "number_of_city": 39,
      "x": -295,
      "y": 16
    },
    {
      "number_of_city": 40,
      "x": 659,
      "y": 682
    },
    {
      "number_of_city": 41,
      "x": -99,
      "y": -216
    },
    {
      "number_of_city": 42,
      "x": 191,
      "y": 27
    },
    {
      "number_of_city": 43,
      "x": -736,
      "y": 651
    },
    {
      "number_of_city": 44,
      "x": 754,
      "y": -300
    },
    {
      "number_of_city": 45,
      "x": 645,
      "y": -984
    },
    {
      "number_of_city": 46,
      "x": -270,
      "y": 460
    },
    {
      "number_of_city": 47,
      "x": -126,
      "y": -573
    }
  ],
  "distance_matrix": {
    "0": {
      "47": 586.6898669655034
    },
    "1": {
      "47": 774.9354811853694
    },
    "2": {
      "47": 1120.8443246053396
    },
    "3": {
      "47": 760.4485518429238
    },
    "4": {
      "47": 903.5955953854578
    },
    "5": {
      "47": 1093.8820777396438
    },
    "6": {
      "47": 389.91922240382047
    },
    "7": {
      "47": 1547.520597601208
    },
    "8": {
      "47": 1275.539885695465
    },
    "9": {
      "47": 1362.7765774329994
    },
    "10": {
      "47": 1800.2499826412998
    },
    "11": {
      "47": 1244.9148565263408
    },
    "12": {
      "47": 911.2738337075195
    },
    "13": {
      "47": 762.3135837698289
    },
    "14": {
      "47": 531.7527620990793
    },
    "15": {
      "47": 733.3212120210352
    },
    "16": {
      "47": 778.9332448932963
    },
    "17": {
      "47": 995.1582788682412
    },
    "18": {
      "47": 258.14724480420085
    },
    "19": {
      "47": 540.4479623423517
    },
    "20": {
      "47": 1780.078649947805
    },
    "21": {
      "47": 451.1163929630578
    },
    "22": {
      "47": 477.557326401763
    },
    "23": {
      "47": 1820.806963958563
    },
    "24": {
      "47": 1394.6400969425767
    },
    "25": {
      "47": 1023.0395886768019
    },
    "26": {
      "47": 1061.6896910114556
    },
    "27": {
      "47": 495.49268410340835
    },
    "28": {
      "47": 1587.212966176877
    },
    "29": {
      "47": 1140.527071138603
    },
    "30": {
      "47": 745.0328851802449
    },
    "31": {
      "47": 1311.396583799119
    },
    "32": {
      "47": 1570.4117294518658
    },
    "33": {
      "47": 1225.7650672131263
    },
    "34": {
      "47": 336.5070578754627
    },
    "35": {
      "47": 1125.4514649686143
    },
    "36": {
      "47": 1027.814185541336
    },
    "37": {
      "47": 1524.6694723775379
    },
    "38": {
      "47": 472.27110858065413
    },
    "39": {
      "47": 612.765860667841
    },
    "40": {
      "47": 1480.287134308746
    },
    "41": {
      "47": 358.0195525386847
    },
    "42": {
      "47": 678.5933981405949
    },
    "43": {
      "47": 1367.5803449889152
    },
    "44": {
      "47": 921.3734313512628
    },
    "45": {
      "47": 873.7059001746526
    },
    "46": {
      "47": 1042.9884946632922
    },
    "47": {
      "47": 0.0
    }
  },
  "stats": {
    "x": {
      "min": -993,
      "avg": 123.70833333333333,
      "stdev": 551.1098264231385,
      "median": 189.5,
      "q1": -185.75,
      "q3": 624.0,
      "max": 978
    },
    "y": {
      "min": -984,
      "avg": 85.29166666666667,
      "stdev": 579.5548533263996,
      "median": 116.0,
      "q1": -382.0,
      "q3": 586.25,
      "max": 995
    }
  }
}