{
  "cities": [
    {
      "number_of_city": 0,
      "x": 0,
      "y": 0
    },
    {
      "number_of_city": 1,
      "x": 330,
      "y": 635
    },
    {
      "number_of_city": 2,
      "x": -729,
      "y": 881
    },
    {
      "number_of_city": 3,
      "x": -207,
      "y": 277
    },
    {
      "number_of_city": 4,
      "x": -954,
      "y": -836
    },
    {
      "number_of_city": 5,
      "x": -718,
      "y": -348
    },
    {
      "number_of_city": 6,
      "x": -21,
      "y": -399
    },
    {
      "number_of_city": 7,
      "x": -166,
      "y": -25
    },
    {
      "number_of_city": 8,
      "x": -398,
      "y": 688
    },
    {
      "number_of_city": 9,
      "x": 943,
      "y": -720
    },
    {
      "number_of_city": 10,
      "x": 993,
      "y": 595
    },
    {
      "number_of_city": 11,
      "x": -507,
      "y": -760
    },
    {
      "number_of_city": 12,
      "x": 892,
      "y": 52
    },
    {
      "number_of_city": 13,
      "x": 897,
      "y": -382
    },
    {
      "number_of_city": 14,
      "x": -801,
      "y": -92
    },
    {
      "number_of_city": 15,
      "x": -12,
      "y": -598
    },
    {
      "number_of_city": 16,
      "x": 679,
      "y": 284
    },
    {
      "number_of_city": 17,
      "x": 455,
      "y": 251
    },
    {
      "number_of_city": 18,
      "x": 685,
      "y": 653
    },
    {
      "number_of_city": 19,
      "x": 888,
      "y": 369
    },
    {
      "number_of_city": 20,
      "x": 509,
      "y": -413
    },
    {
      "number_of_city": 21,
      "x": 237,
      "y": -387
    },
    {
      "number_of_city": 22,
      "x": 365,
      "y": 967
    },
    {
      "number_of_city": 23,
      "x": 309,
      "y": -135
    },
    {
      "number_of_city": 24,
      "x": 635,
      "y": 148
    },
    {
      "number_of_city": 25,
      "x": -217,
      "y": -334
    },
    {
      "number_of_city": 26,
      "x": 754,
      "y": 759
    },
    {
      "number_of_city": 27,
      "x": -664,
      "y": -882
    },
    {
      "number_of_city": 28,
      "x": 769,
      "y": -765
    },
    {
      "number_of_city": 29,
      "x": -728,
      "y": 104
    },
    {
      "number_of_city": 30,
      "x": 885,
      "y": 232
    },
    {
      "number_of_city": 31,
      "x": 673,
      "y": -113
    },
    {
      "number_of_city": 32,
      "x": 195,
      "y": -404
    },
    {
      "number_of_city": 33,
      "x": 421,
      "y": -908
    }
  ],
  "distance_matrix": {
    "0": {
      "33": 1000.8521369313252
    },
    "1": {
      "33": 1545.681079653885
    },
    "2": {
      "33": 2126.73952330792
    },
    "3": {
      "33": 1341.1222912173223
    },
    "4": {
      "33": 1376.8838004711945
    },
    "5": {
      "33": 1269.2206269991045
    },
    "6": {
      "33": 674.1253592619106
    },
    "7": {
      "33": 1060.3103319311756
    },
    "8": {
      "33": 1793.872069017186
    },
    "9": {
      "33": 554.8224941366383
    },
    "10": {
      "33": 1608.1644816373728
    },
    "11": {
      "33": 939.7276201112746
    },
    "12": {
      "33": 1069.3180069558355
    },
    "13": {
      "33": 709.4025655437116
    },
    "14": {
      "33": 1469.4012386002673
    },
    "15": {
      "33": 532.5307502858403
    },
    "16": {
      "33": 1219.6015742856353
    },
    "17": {
      "33": 1159.4985985330038
    },
    "18": {
      "33": 1583.1667631680498
    },
    "19": {
      "33": 1359.7124696052472
    },
    "20": {
      "33": 502.7613748091633
    },
    "21": {
      "33": 552.5368765973906
    },
    "22": {
      "33": 1875.8360802586137
    },
    "23": {
      "33": 781.0716996537514
    },
    "24": {
      "33": 1077.4655446927293
    },
    "25": {
      "33": 858.2074341323314
    },
    "26": {
      "33": 1699.9347046283865
    },
    "27": {
      "33": 1085.3114760288863
    },
    "28": {
      "33": 376.2352987161093
    },
    "29": {
      "33": 1531.125403094077
    },
    "30": {
      "33": 1230.8111146719468
    },
    "31": {
      "33": 833.9838127925506
    },
    "32": {
      "33": 552.3513374655664
    },
    "33": {
      "33": 0.0
    }
  },
  "stats": {
    "x": {
      "min": -954,
      "avg": 188.0,
      "stdev": 602.273017724344,
      "median": 319.5,
      "q1": -214.5,
      "q3": 683.5,
      "max": 993
    },
    "y": {
      "min": -908,
      "avg": -47.23529411764706,
      "stdev": 542.603268139223,
      "median": -58.5,
      "q1": -402.75,
      "q3": 282.25,
      "max": 967
    }
  }
}