{
  "cities": [
    {
      "number_of_city": 0,
      "x": 0,
      "y": 0
    },
    {
      "number_of_city": 1,
      "x": -56,
      "y": 105
    },
    {
      "number_of_city": 2,
      "x": 641,
      "y": 913
    },
    {
      "number_of_city": 3,
      "x": -385,
      "y": -547
    },
    {
      "number_of_city": 4,
      "x": -70,
      "y": 102
    },
    {
      "number_of_city": 5,
      "x": 917,
      "y": 975
    },
    {
      "number_of_city": 6,
      "x": 938,
      "y": 626
    },
    {
      "number_of_city": 7,
      "x": -179,
      "y": 258
    },
    {
      "number_of_city": 8,
      "x": -576,
      "y": 232
    },
    {
      "number_of_city": 9,
      "x": 24,
      "y": -611
    },
    {
      "number_of_city": 10,
      "x": -321,
      "y": -538
    },
    {
      "number_of_city": 11,
      "x": -967,
      "y": -547
    },
    {
      "number_of_city": 12,
      "x": -97,
      "y": -94
    },
    {
      "number_of_city": 13,
      "x": -469,
      "y": 414
    },
    {
      "number_of_city": 14,
      "x": -104,
      "y": -898
    }
  ],
  "distance_matrix": {
    "0": {
      "14": 904.0022123866734
    },
    "1": {
      "14": 1004.1478974732756
    },
    "2": {
      "14": 1958.2507500317727
    },
    "3": {
      "14": 449.6242876002141
    },
    "4": {
      "14": 1000.5778330544806
    },
    "5": {
      "14": 2133.206506646743
    },
    "6": {
      "14": 1846.1690063480103
    },
    "7": {
      "14": 1158.4304036065353
    },
    "8": {
      "14": 1224.6158581367465
    },
    "9": {
      "14": 314.2499005568657
    },
    "10": {
      "14": 420.34390681916636
    },
    "11": {
      "14": 931.6490755643994
    },
    "12": {
      "14": 804.0304720593617
    },
    "13": {
      "14": 1361.8256129181887
    },
    "14": {
      "14": 0.0
    }
  },
  "stats": {
    "x": {
      "min": -967,
      "avg": -46.93333333333333,
      "stdev": 527.6323756267462,
      "median": -97.0,
      "q1": -353.0,
      "q3": 12.0,
      "max": 938
    },
    "y": {
      "min": -898,
      "avg": 26.0,
      "stdev": 570.436299185607,
      "median": 102.0,
      "q1": -542.5,
      "q3": 336.0,
      "max": 975
    }
  }
}