{
  "cities": [
    {
      "number_of_city": 0,
      "x": 0,
      "y": 0
    },
    {
      "number_of_city": 1,
      "x": 521,
      "y": -782
    },
    {
      "number_of_city": 2,
      "x": -537,
      "y": 780
    },
    {
      "number_of_city": 3,
      "x": 687,
      "y": 761
    },
    {
      "number_of_city": 4,
      "x": 11,
      "y": 556
    },
    {
      "number_of_city": 5,
      "x": -675,
      "y": -495
    },
    {
      "number_of_city": 6,
      "x": -924,
      "y": -788
    },
    {
      "number_of_city": 7,
      "x": -276,
      "y": 90
    },
    {
      "number_of_city": 8,
      "x": 627,
      "y": 992
    },
    {
      "number_of_city": 9,
      "x": 329,
      "y": -503
    },
    {
      "number_of_city": 10,
      "x": -815,
      "y": 300
    },
    {
      "number_of_city": 11,
      "x": -712,
      "y": -402
    },
    {
      "number_of_city": 12,
      "x": 530,
      "y": 383
    },
    {
      "number_of_city": 13,
      "x": 887,
      "y": 759
    },
    {
      "number_of_city": 14,
      "x": 250,
      "y": -818
    }
  ],
  "distance_matrix": {
    "0": {
      "14": 855.3502206698728
    },
    "1": {
      "14": 273.3806869550225
    },
    "2": {
      "14": 1781.2840873931368
    },
    "3": {
      "14": 1638.3558831951011
    },
    "4": {
      "14": 1394.6314925456115
    },
    "5": {
      "14": 979.7724225553605
    },
    "6": {
      "14": 1174.383242387254
    },
    "7": {
      "14": 1049.3521811098503
    },
    "8": {
      "14": 1848.8453153252167
    },
    "9": {
      "14": 324.7552924895913
    },
    "10": {
      "14": 1544.0689751432737
    },
    "11": {
      "14": 1048.0935072788116
    },
    "12": {
      "14": 1233.2076062042433
    },
    "13": {
      "14": 1700.793344295538
    },
    "14": {
      "14": 0.0
    }
  },
  "stats": {
    "x": {
      "min": -924,
      "avg": -6.466666666666667,
      "stdev": 610.5944254420871,
      "median": 11.0,
      "q1": -606.0,
      "q3": 525.5,
      "max": 887
    },
    "y": {
      "min": -818,
      "avg": 55.53333333333333,
      "stdev": 644.5686117381882,
      "median": 90.0,
      "q1": -499.0,
      "q3": 657.5,
      "max": 992
    }
  }
}