{"cities": [{"number_of_city": 0, "x": 0, "y": 0}, {"number_of_city": 1, "x": 667, "y": 577}, {"number_of_city": 2, "x": 915, "y": -603}, {"number_of_city": 3, "x": 359, "y": 610}, {"number_of_city": 4, "x": 837, "y": -603}, {"number_of_city": 5, "x": 352, "y": -172}, {"number_of_city": 6, "x": 823, "y": -671}, {"number_of_city": 7, "x": -563, "y": -442}, {"number_of_city": 8, "x": 454, "y": -527}], "distance_matrix": {"0": {"8": 695.5896778992627}, "1": {"8": 1124.3598178519187}, "2": {"8": 467.22264499914814}, "3": {"8": 1140.961874910814}, "4": {"8": 390.4676683158287}, "5": {"8": 369.36296511697003}, "6": {"8": 396.10225952397695}, "7": {"8": 1020.5459323322983}, "8": {"8": 0.0}}, "stats": {"x": {"min": -563, "avg": 427.1111111111111, "stdev": 473.55924773053596, "median": 454.0, "q1": 352.0, "q3": 823.0, "max": 915}, "y": {"min": -671, "avg": -203.44444444444446, "stdev": 501.5797820664004, "median": -442.0, "q1": -603.0, "q3": 0.0, "max": 610}}}