{
  "used_read_access_memory_in_bytes": [
    6897049600,
    6903017472,
    6902972416,
    6902951936,
    6902964224,
    6902968320,
    6902886400,
    6902915072,
    6903160832,
    6903099392,
    6903078912,
    6903054336,
    6902992896,
    6902996992,
    6902198272,
    6902169600,
    6902374400,
    6902394880,
    6902370304,
    6902407168,
    6902628352,
    6902665216,
    6876995584
  ],
  "utilization_of_cpu": [
    13.5,
    12.5,
    18.8,
    13.9,
    12.0,
    12.5,
    12.5,
    12.5,
    12.5,
    12.5,
    12.5,
    12.5,
    16.2,
    12.5,
    12.5,
    12.9,
    12.5,
    12.9,
    12.5,
    12.7,
    12.5,
    16.2,
    12.5
  ],
  "used_read_access_memory_in_percentage": [
    40.6,
    40.6,
    40.6,
    40.6,
    40.6,
    40.6,
    40.6,
    40.6,
    40.6,
    40.6,
    40.6,
    40.6,
    40.6,
    40.6,
    40.6,
    40.6,
    40.6,
    40.6,
    40.6,
    40.6,
    40.6,
    40.6,
    40.5
  ],
  "time_duration_with_cpu_profiler_in_sec": 24.9743985,
  "used_algorithm": "ant_colony_tsp_scikit_opt",
  "name_of_src_file": "TSP_CITIES_SET_90_N_11.json"
}