{
  "cities": [
    {
      "number_of_city": 0,
      "x": 0,
      "y": 0
    },
    {
      "number_of_city": 1,
      "x": 889,
      "y": -905
    },
    {
      "number_of_city": 2,
      "x": 617,
      "y": -150
    },
    {
      "number_of_city": 3,
      "x": -222,
      "y": 499
    },
    {
      "number_of_city": 4,
      "x": -305,
      "y": 518
    },
    {
      "number_of_city": 5,
      "x": 390,
      "y": 973
    },
    {
      "number_of_city": 6,
      "x": 110,
      "y": 408
    },
    {
      "number_of_city": 7,
      "x": -485,
      "y": -503
    },
    {
      "number_of_city": 8,
      "x": -258,
      "y": 614
    },
    {
      "number_of_city": 9,
      "x": 837,
      "y": 582
    },
    {
      "number_of_city": 10,
      "x": 43,
      "y": 581
    },
    {
      "number_of_city": 11,
      "x": 223,
      "y": -231
    },
    {
      "number_of_city": 12,
      "x": 59,
      "y": -260
    },
    {
      "number_of_city": 13,
      "x": 244,
      "y": -900
    },
    {
      "number_of_city": 14,
      "x": -30,
      "y": 936
    },
    {
      "number_of_city": 15,
      "x": -425,
      "y": 639
    },
    {
      "number_of_city": 16,
      "x": -139,
      "y": 443
    },
    {
      "number_of_city": 17,
      "x": 57,
      "y": 678
    },
    {
      "number_of_city": 18,
      "x": 341,
      "y": 531
    },
    {
      "number_of_city": 19,
      "x": 199,
      "y": -28
    },
    {
      "number_of_city": 20,
      "x": -853,
      "y": -186
    },
    {
      "number_of_city": 21,
      "x": -251,
      "y": 751
    },
    {
      "number_of_city": 22,
      "x": -18,
      "y": -385
    },
    {
      "number_of_city": 23,
      "x": 440,
      "y": 915
    },
    {
      "number_of_city": 24,
      "x": -207,
      "y": -959
    },
    {
      "number_of_city": 25,
      "x": 225,
      "y": 927
    },
    {
      "number_of_city": 26,
      "x": -644,
      "y": 253
    },
    {
      "number_of_city": 27,
      "x": -941,
      "y": 189
    },
    {
      "number_of_city": 28,
      "x": 435,
      "y": 106
    },
    {
      "number_of_city": 29,
      "x": 555,
      "y": -586
    },
    {
      "number_of_city": 30,
      "x": -705,
      "y": 514
    },
    {
      "number_of_city": 31,
      "x": -336,
      "y": 63
    },
    {
      "number_of_city": 32,
      "x": 624,
      "y": -338
    },
    {
      "number_of_city": 33,
      "x": 135,
      "y": 245
    },
    {
      "number_of_city": 34,
      "x": -442,
      "y": 171
    }
  ],
  "distance_matrix": {
    "0": {
      "34": 473.92509956743163
    },
    "1": {
      "34": 1711.5306015376996
    },
    "2": {
      "34": 1106.5812216010174
    },
    "3": {
      "34": 394.94809785590814
    },
    "4": {
      "34": 373.06567786383135
    },
    "5": {
      "34": 1155.6071997006595
    },
    "6": {
      "34": 600.7270594870852
    },
    "7": {
      "34": 675.3702688155587
    },
    "8": {
      "34": 479.69260990763655
    },
    "9": {
      "34": 1343.414306906101
    },
    "10": {
      "34": 635.0787352761861
    },
    "11": {
      "34": 777.0643473998791
    },
    "12": {
      "34": 660.8797167412539
    },
    "13": {
      "34": 1271.8635933149435
    },
    "14": {
      "34": 868.8895211705571
    },
    "15": {
      "34": 468.30865889923496
    },
    "16": {
      "34": 407.17686574755203
    },
    "17": {
      "34": 711.3719139803032
    },
    "18": {
      "34": 861.794058925913
    },
    "19": {
      "34": 671.1795586875393
    },
    "20": {
      "34": 544.3987509170094
    },
    "21": {
      "34": 610.6398283767609
    },
    "22": {
      "34": 699.2224252696706
    },
    "23": {
      "34": 1153.8890761247374
    },
    "24": {
      "34": 1154.177196101188
    },
    "25": {
      "34": 1008.1790515578074
    },
    "26": {
      "34": 218.00917411888886
    },
    "27": {
      "34": 499.3245437588663
    },
    "28": {
      "34": 879.4054809926988
    },
    "29": {
      "34": 1251.8218723125108
    },
    "30": {
      "34": 432.2244787144754
    },
    "31": {
      "34": 151.32745950421557
    },
    "32": {
      "34": 1181.2861634675994
    },
    "33": {
      "34": 581.725880462611
    },
    "34": {
      "34": 0.0
    }
  },
  "stats": {
    "x": {
      "min": -941,
      "avg": 4.628571428571429,
      "stdev": 455.1037429056398,
      "median": 43.0,
      "q1": -281.5,
      "q3": 292.5,
      "max": 889
    },
    "y": {
      "min": -959,
      "avg": 174.42857142857142,
      "stdev": 546.5559702092993,
      "median": 245.0,
      "q1": -208.5,
      "q3": 581.5,
      "max": 973
    }
  }
}