{
  "used_read_access_memory_in_bytes": [
    8174411776,
    8164356096,
    8180805632,
    8188981248,
    8188915712,
    8188985344,
    8188821504,
    8188727296,
    8188428288,
    8188510208,
    8185819136,
    8189595648,
    8179142656,
    8185225216,
    8184934400,
    8189288448,
    8189251584,
    8188846080,
    8189059072,
    8189095936
  ],
  "utilization_of_cpu": [
    17.9,
    21.4,
    25.0,
    31.2,
    25.0,
    25.0,
    25.0,
    26.6,
    25.0,
    32.3,
    27.9,
    29.2,
    15.6,
    12.5,
    12.5,
    12.5,
    12.5,
    12.5,
    17.2,
    25.0
  ],
  "used_read_access_memory_in_percentage": [
    48.1,
    48.0,
    48.1,
    48.2,
    48.2,
    48.2,
    48.2,
    48.2,
    48.2,
    48.2,
    48.2,
    48.2,
    48.1,
    48.2,
    48.1,
    48.2,
    48.2,
    48.2,
    48.2,
    48.2
  ],
  "time_duration_with_cpu_profiler_in_sec": 21.2016877,
  "used_algorithm": "ant_colony_tsp_scikit_opt",
  "name_of_src_file": "TSP_CITIES_SET_65_N_8.json"
}