{"cities": [{"number_of_city": 0, "x": 0, "y": 0}, {"number_of_city": 1, "x": 261, "y": 815}, {"number_of_city": 2, "x": -927, "y": -639}, {"number_of_city": 3, "x": -37, "y": -549}, {"number_of_city": 4, "x": -512, "y": 655}, {"number_of_city": 5, "x": -824, "y": 146}, {"number_of_city": 6, "x": 730, "y": 703}, {"number_of_city": 7, "x": 547, "y": -36}, {"number_of_city": 8, "x": -939, "y": 952}, {"number_of_city": 9, "x": -848, "y": 925}, {"number_of_city": 10, "x": 531, "y": -32}, {"number_of_city": 11, "x": -397, "y": 848}, {"number_of_city": 12, "x": -794, "y": 319}, {"number_of_city": 13, "x": -606, "y": 469}, {"number_of_city": 14, "x": 644, "y": -789}, {"number_of_city": 15, "x": -798, "y": -304}], "distance_matrix": {"0": {"15": 853.9437920612808}, "1": {"15": 1540.6628443627762}, "2": {"15": 358.97910802719423}, "3": {"15": 799.4660718254403}, "4": {"15": 1000.7382275100717}, "5": {"15": 450.75048530201275}, "6": {"15": 1829.98169389751}, "7": {"15": 1371.4404835792182}, "8": {"15": 1263.8896312574132}, "9": {"15": 1230.0166665537504}, "10": {"15": 1356.548930190135}, "11": {"15": 1219.7971142776162}, "12": {"15": 623.0128409591571}, "13": {"15": 796.487915790315}, "14": {"15": 1521.377336494796}, "15": {"15": 0.0}}, "stats": {"x": {"min": -939, "avg": -248.0625, "stdev": 622.2054825377224, "median": -454.5, "q1": -804.5, "q3": 328.5, "max": 730}, "y": {"min": -789, "avg": 217.6875, "stdev": 581.9681226951639, "median": 232.5, "q1": -103.0, "q3": 731.0, "max": 952}}}