{"cities": [{"number_of_city": 0, "x": 0, "y": 0}, {"number_of_city": 1, "x": -880, "y": -9}, {"number_of_city": 2, "x": 317, "y": -748}, {"number_of_city": 3, "x": -563, "y": -11}, {"number_of_city": 4, "x": -602, "y": -96}, {"number_of_city": 5, "x": 906, "y": 682}, {"number_of_city": 6, "x": 190, "y": 770}, {"number_of_city": 7, "x": 19, "y": -312}, {"number_of_city": 8, "x": -49, "y": 831}, {"number_of_city": 9, "x": 414, "y": 634}, {"number_of_city": 10, "x": -985, "y": -769}, {"number_of_city": 11, "x": -211, "y": 947}], "distance_matrix": {"0": {"11": 970.2216241663551}, "1": {"11": 1166.832035898912}, "2": {"11": 1775.333489798466}, "3": {"11": 1020.6213793567133}, "4": {"11": 1113.8806040146314}, "5": {"11": 1148.004355392435}, "6": {"11": 438.3263624287273}, "7": {"11": 1279.8363176594107}, "8": {"11": 199.24858845171275}, "9": {"11": 698.9949928289901}, "10": {"11": 1882.4802787811616}, "11": {"11": 0.0}}, "stats": {"x": {"min": -985, "avg": -120.33333333333333, "stdev": 558.1088739229248, "median": -24.5, "q1": -572.75, "q3": 221.75, "max": 906}, "y": {"min": -769, "avg": 159.91666666666666, "stdev": 602.8792217854302, "median": -4.5, "q1": -150.0, "q3": 704.0, "max": 947}}}