{
  "cities": [
    {
      "number_of_city": 0,
      "x": 0,
      "y": 0
    },
    {
      "number_of_city": 1,
      "x": 881,
      "y": 954
    },
    {
      "number_of_city": 2,
      "x": 81,
      "y": 562
    },
    {
      "number_of_city": 3,
      "x": -44,
      "y": -510
    },
    {
      "number_of_city": 4,
      "x": 790,
      "y": 63
    },
    {
      "number_of_city": 5,
      "x": 270,
      "y": 973
    },
    {
      "number_of_city": 6,
      "x": 65,
      "y": 598
    },
    {
      "number_of_city": 7,
      "x": -338,
      "y": -521
    },
    {
      "number_of_city": 8,
      "x": 507,
      "y": 553
    },
    {
      "number_of_city": 9,
      "x": -830,
      "y": -531
    },
    {
      "number_of_city": 10,
      "x": 525,
      "y": 900
    },
    {
      "number_of_city": 11,
      "x": 625,
      "y": 645
    }
  ],
  "distance_matrix": {
    "0": {
      "11": 898.1369606023349
    },
    "1": {
      "11": 401.26923629902154
    },
    "2": {
      "11": 550.2953752304302
    },
    "3": {
      "11": 1334.7606527014498
    },
    "4": {
      "11": 604.9371868219047
    },
    "5": {
      "11": 483.3311494203534
    },
    "6": {
      "11": 561.9688603472616
    },
    "7": {
      "11": 1512.2582451420128
    },
    "8": {
      "11": 149.6262009141447
    },
    "9": {
      "11": 1870.8289606481935
    },
    "10": {
      "11": 273.9069184960467
    },
    "11": {
      "11": 0.0
    }
  },
  "stats": {
    "x": {
      "min": -830,
      "avg": 211.0,
      "stdev": 493.41794933633366,
      "median": 175.5,
      "q1": -11.0,
      "q3": 550.0,
      "max": 881
    },
    "y": {
      "min": -531,
      "avg": 307.1666666666667,
      "stdev": 583.6703355542927,
      "median": 557.5,
      "q1": -127.5,
      "q3": 708.75,
      "max": 973
    }
  }
}