{
  "cities": [
    {
      "number_of_city": 0,
      "x": 0,
      "y": 0
    },
    {
      "number_of_city": 1,
      "x": 848,
      "y": -586
    },
    {
      "number_of_city": 2,
      "x": 77,
      "y": 963
    },
    {
      "number_of_city": 3,
      "x": -394,
      "y": 924
    },
    {
      "number_of_city": 4,
      "x": 858,
      "y": 403
    },
    {
      "number_of_city": 5,
      "x": -454,
      "y": 850
    },
    {
      "number_of_city": 6,
      "x": -144,
      "y": 836
    },
    {
      "number_of_city": 7,
      "x": 456,
      "y": -930
    },
    {
      "number_of_city": 8,
      "x": -545,
      "y": -229
    },
    {
      "number_of_city": 9,
      "x": 166,
      "y": 809
    },
    {
      "number_of_city": 10,
      "x": -791,
      "y": 610
    },
    {
      "number_of_city": 11,
      "x": 519,
      "y": 331
    },
    {
      "number_of_city": 12,
      "x": -285,
      "y": 342
    },
    {
      "number_of_city": 13,
      "x": 427,
      "y": -619
    },
    {
      "number_of_city": 14,
      "x": -575,
      "y": -13
    },
    {
      "number_of_city": 15,
      "x": -917,
      "y": 365
    },
    {
      "number_of_city": 16,
      "x": 625,
      "y": -244
    },
    {
      "number_of_city": 17,
      "x": 979,
      "y": -512
    },
    {
      "number_of_city": 18,
      "x": -954,
      "y": 90
    },
    {
      "number_of_city": 19,
      "x": 295,
      "y": 490
    },
    {
      "number_of_city": 20,
      "x": -397,
      "y": -945
    }
  ],
  "distance_matrix": {
    "0": {
      "20": 1025.0043902345003
    },
    "1": {
      "20": 1295.7260512932507
    },
    "2": {
      "20": 1965.995930819797
    },
    "3": {
      "20": 1869.0024077031042
    },
    "4": {
      "20": 1841.7733302445229
    },
    "5": {
      "20": 1795.9047858948425
    },
    "6": {
      "20": 1798.8802072400485
    },
    "7": {
      "20": 853.1318772616576
    },
    "8": {
      "20": 731.1361022408892
    },
    "9": {
      "20": 1842.14141693845
    },
    "10": {
      "20": 1604.1387097130971
    },
    "11": {
      "20": 1570.7424995841934
    },
    "12": {
      "20": 1291.8641569453036
    },
    "13": {
      "20": 886.1444577494124
    },
    "14": {
      "20": 948.8456144178567
    },
    "15": {
      "20": 1409.432509913121
    },
    "16": {
      "20": 1239.3082748049414
    },
    "17": {
      "20": 1442.5203638077348
    },
    "18": {
      "20": 1175.3612210720582
    },
    "19": {
      "20": 1593.138098219988
    },
    "20": {
      "20": 0.0
    }
  },
  "stats": {
    "x": {
      "min": -954,
      "avg": -9.80952380952381,
      "stdev": 600.3210490269036,
      "median": 0.0,
      "q1": -454.0,
      "q3": 456.0,
      "max": 979
    },
    "y": {
      "min": -945,
      "avg": 139.76190476190476,
      "stdev": 610.2479745777043,
      "median": 331.0,
      "q1": -244.0,
      "q3": 610.0,
      "max": 963
    }
  }
}