{
  "cities": [
    {
      "number_of_city": 0,
      "x": 0,
      "y": 0
    },
    {
      "number_of_city": 1,
      "x": 991,
      "y": 53
    },
    {
      "number_of_city": 2,
      "x": -425,
      "y": 808
    },
    {
      "number_of_city": 3,
      "x": 685,
      "y": 664
    },
    {
      "number_of_city": 4,
      "x": -632,
      "y": -326
    },
    {
      "number_of_city": 5,
      "x": -467,
      "y": -261
    },
    {
      "number_of_city": 6,
      "x": 117,
      "y": 225
    },
    {
      "number_of_city": 7,
      "x": 706,
      "y": -661
    },
    {
      "number_of_city": 8,
      "x": -167,
      "y": 898
    },
    {
      "number_of_city": 9,
      "x": 256,
      "y": 941
    },
    {
      "number_of_city": 10,
      "x": 581,
      "y": 528
    },
    {
      "number_of_city": 11,
      "x": 772,
      "y": 463
    },
    {
      "number_of_city": 12,
      "x": 942,
      "y": -300
    },
    {
      "number_of_city": 13,
      "x": -209,
      "y": 559
    },
    {
      "number_of_city": 14,
      "x": -304,
      "y": 509
    },
    {
      "number_of_city": 15,
      "x": 99,
      "y": -691
    },
    {
      "number_of_city": 16,
      "x": 510,
      "y": -1
    },
    {
      "number_of_city": 17,
      "x": -199,
      "y": 550
    },
    {
      "number_of_city": 18,
      "x": -497,
      "y": 636
    },
    {
      "number_of_city": 19,
      "x": -861,
      "y": 779
    },
    {
      "number_of_city": 20,
      "x": 895,
      "y": -963
    }
  ],
  "distance_matrix": {
    "0": {
      "20": 1314.6839924483754
    },
    "1": {
      "20": 1020.5253549030518
    },
    "2": {
      "20": 2208.809860535759
    },
    "3": {
      "20": 1640.4965711637437
    },
    "4": {
      "20": 1654.5386063794342
    },
    "5": {
      "20": 1532.2689059039212
    },
    "6": {
      "20": 1420.0802794208503
    },
    "7": {
      "20": 356.2653505464712
    },
    "8": {
      "20": 2142.700399029225
    },
    "9": {
      "20": 2008.3667493762189
    },
    "10": {
      "20": 1523.7050239465643
    },
    "11": {
      "20": 1431.2948682923445
    },
    "12": {
      "20": 664.6638248016812
    },
    "13": {
      "20": 1880.239346466295
    },
    "14": {
      "20": 1898.5217933961148
    },
    "15": {
      "20": 841.1896337925236
    },
    "16": {
      "20": 1036.1800036673164
    },
    "17": {
      "20": 1867.0846258271208
    },
    "18": {
      "20": 2120.0153301332516
    },
    "19": {
      "20": 2473.4793308212625
    },
    "20": {
      "20": 0.0
    }
  },
  "stats": {
    "x": {
      "min": -861,
      "avg": 133.0,
      "stdev": 571.8123818176728,
      "median": 99.0,
      "q1": -304.0,
      "q3": 685.0,
      "max": 991
    },
    "y": {
      "min": -963,
      "avg": 210.0,
      "stdev": 565.5837692154894,
      "median": 463.0,
      "q1": -261.0,
      "q3": 636.0,
      "max": 941
    }
  }
}