{
  "cities": [
    {
      "number_of_city": 0,
      "x": 0,
      "y": 0
    },
    {
      "number_of_city": 1,
      "x": -502,
      "y": -741
    },
    {
      "number_of_city": 2,
      "x": -95,
      "y": -365
    },
    {
      "number_of_city": 3,
      "x": 253,
      "y": -117
    },
    {
      "number_of_city": 4,
      "x": -582,
      "y": 8
    },
    {
      "number_of_city": 5,
      "x": 656,
      "y": 817
    },
    {
      "number_of_city": 6,
      "x": 670,
      "y": 939
    },
    {
      "number_of_city": 7,
      "x": -733,
      "y": -310
    },
    {
      "number_of_city": 8,
      "x": -197,
      "y": 600
    },
    {
      "number_of_city": 9,
      "x": 349,
      "y": 946
    },
    {
      "number_of_city": 10,
      "x": 993,
      "y": -520
    },
    {
      "number_of_city": 11,
      "x": -487,
      "y": 383
    },
    {
      "number_of_city": 12,
      "x": 413,
      "y": -101
    }
  ],
  "distance_matrix": {
    "0": {
      "12": 425.1705540133277
    },
    "1": {
      "12": 1116.6131827987704
    },
    "2": {
      "12": 572.5032750998024
    },
    "3": {
      "12": 160.79800993793424
    },
    "4": {
      "12": 1000.9525463277467
    },
    "5": {
      "12": 949.6172913337247
    },
    "6": {
      "12": 1071.2838092681136
    },
    "7": {
      "12": 1164.902141812779
    },
    "8": {
      "12": 929.2475450599802
    },
    "9": {
      "12": 1048.9542411373338
    },
    "10": {
      "12": 715.5145002024767
    },
    "11": {
      "12": 1021.8884479237447
    },
    "12": {
      "12": 0.0
    }
  },
  "stats": {
    "x": {
      "min": -733,
      "avg": 56.76923076923077,
      "stdev": 547.1736704566711,
      "median": 0.0,
      "q1": -487.0,
      "q3": 413.0,
      "max": 993
    },
    "y": {
      "min": -741,
      "avg": 118.38461538461539,
      "stdev": 565.7871417269836,
      "median": 0.0,
      "q1": -310.0,
      "q3": 600.0,
      "max": 946
    }
  }
}