{
  "cities": [
    {
      "number_of_city": 0,
      "x": 0,
      "y": 0
    },
    {
      "number_of_city": 1,
      "x": -383,
      "y": -43
    },
    {
      "number_of_city": 2,
      "x": -892,
      "y": 866
    },
    {
      "number_of_city": 3,
      "x": -57,
      "y": 584
    },
    {
      "number_of_city": 4,
      "x": 364,
      "y": -698
    },
    {
      "number_of_city": 5,
      "x": 718,
      "y": -109
    },
    {
      "number_of_city": 6,
      "x": -408,
      "y": 976
    },
    {
      "number_of_city": 7,
      "x": -128,
      "y": 962
    },
    {
      "number_of_city": 8,
      "x": 839,
      "y": 462
    },
    {
      "number_of_city": 9,
      "x": 317,
      "y": 277
    },
    {
      "number_of_city": 10,
      "x": 543,
      "y": 532
    },
    {
      "number_of_city": 11,
      "x": -783,
      "y": -570
    },
    {
      "number_of_city": 12,
      "x": -382,
      "y": -215
    },
    {
      "number_of_city": 13,
      "x": -815,
      "y": -138
    },
    {
      "number_of_city": 14,
      "x": 558,
      "y": -482
    },
    {
      "number_of_city": 15,
      "x": -292,
      "y": -952
    },
    {
      "number_of_city": 16,
      "x": 297,
      "y": -266
    },
    {
      "number_of_city": 17,
      "x": -713,
      "y": -27
    },
    {
      "number_of_city": 18,
      "x": -71,
      "y": 586
    },
    {
      "number_of_city": 19,
      "x": 982,
      "y": -950
    },
    {
      "number_of_city": 20,
      "x": 351,
      "y": -282
    },
    {
      "number_of_city": 21,
      "x": -769,
      "y": -489
    },
    {
      "number_of_city": 22,
      "x": -703,
      "y": -555
    },
    {
      "number_of_city": 23,
      "x": 797,
      "y": -782
    },
    {
      "number_of_city": 24,
      "x": 520,
      "y": 120
    },
    {
      "number_of_city": 25,
      "x": 587,
      "y": 683
    },
    {
      "number_of_city": 26,
      "x": 5,
      "y": 825
    },
    {
      "number_of_city": 27,
      "x": -472,
      "y": 976
    },
    {
      "number_of_city": 28,
      "x": -552,
      "y": 333
    },
    {
      "number_of_city": 29,
      "x": 58,
      "y": 982
    },
    {
      "number_of_city": 30,
      "x": 898,
      "y": 8
    },
    {
      "number_of_city": 31,
      "x": -212,
      "y": 602
    },
    {
      "number_of_city": 32,
      "x": -662,
      "y": 449
    },
    {
      "number_of_city": 33,
      "x": 408,
      "y": 866
    },
    {
      "number_of_city": 34,
      "x": 676,
      "y": 375
    },
    {
      "number_of_city": 35,
      "x": 119,
      "y": 551
    },
    {
      "number_of_city": 36,
      "x": 485,
      "y": 720
    },
    {
      "number_of_city": 37,
      "x": -514,
      "y": -761
    },
    {
      "number_of_city": 38,
      "x": -459,
      "y": -975
    },
    {
      "number_of_city": 39,
      "x": 823,
      "y": -258
    },
    {
      "number_of_city": 40,
      "x": -586,
      "y": -511
    }
  ],
  "distance_matrix": {
    "0": {
      "40": 777.5069131525455
    },
    "1": {
      "40": 510.13037549238334
    },
    "2": {
      "40": 1410.5903019658117
    },
    "3": {
      "40": 1216.0863456185996
    },
    "4": {
      "40": 968.2298280883522
    },
    "5": {
      "40": 1364.5585366703767
    },
    "6": {
      "40": 1497.6157718186598
    },
    "7": {
      "40": 1542.5605336582419
    },
    "8": {
      "40": 1725.501086641211
    },
    "9": {
      "40": 1198.4794533073982
    },
    "10": {
      "40": 1537.0393618902542
    },
    "11": {
      "40": 205.64532574313475
    },
    "12": {
      "40": 359.4885255470611
    },
    "13": {
      "40": 437.6871028485989
    },
    "14": {
      "40": 1144.3675108984876
    },
    "15": {
      "40": 530.0160374932065
    },
    "16": {
      "40": 916.3590999166211
    },
    "17": {
      "40": 500.38485188902354
    },
    "18": {
      "40": 1211.8721054632786
    },
    "19": {
      "40": 1628.295120670697
    },
    "20": {
      "40": 964.5776277729025
    },
    "21": {
      "40": 184.31766057543157
    },
    "22": {
      "40": 125.0
    },
    "23": {
      "40": 1409.3012452985345
    },
    "24": {
      "40": 1273.3408813039814
    },
    "25": {
      "40": 1673.7876209364197
    },
    "26": {
      "40": 1460.8822676725185
    },
    "27": {
      "40": 1491.3634701171945
    },
    "28": {
      "40": 844.6845565061551
    },
    "29": {
      "40": 1625.972016979382
    },
    "30": {
      "40": 1572.1377166139105
    },
    "31": {
      "40": 1174.1571445083491
    },
    "32": {
      "40": 963.0036344687386
    },
    "33": {
      "40": 1698.2829564003755
    },
    "34": {
      "40": 1541.9597919530847
    },
    "35": {
      "40": 1274.7034949351946
    },
    "36": {
      "40": 1631.6868572124984
    },
    "37": {
      "40": 260.161488310626
    },
    "38": {
      "40": 481.06652346634974
    },
    "39": {
      "40": 1431.5341421007045
    },
    "40": {
      "40": 0.0
    }
  },
  "stats": {
    "x": {
      "min": -892,
      "avg": 12.0,
      "stdev": 567.9674286435799,
      "median": 0.0,
      "q1": -472.0,
      "q3": 520.0,
      "max": 982
    },
    "y": {
      "min": -975,
      "avg": 89.5609756097561,
      "stdev": 614.8587662537019,
      "median": 8.0,
      "q1": -482.0,
      "q3": 586.0,
      "max": 982
    }
  }
}