{
  "cities": [
    {
      "number_of_city": 0,
      "x": 0,
      "y": 0
    },
    {
      "number_of_city": 1,
      "x": -82,
      "y": 445
    },
    {
      "number_of_city": 2,
      "x": -394,
      "y": -254
    },
    {
      "number_of_city": 3,
      "x": 974,
      "y": 420
    },
    {
      "number_of_city": 4,
      "x": 829,
      "y": -265
    },
    {
      "number_of_city": 5,
      "x": -768,
      "y": 693
    },
    {
      "number_of_city": 6,
      "x": 707,
      "y": -53
    },
    {
      "number_of_city": 7,
      "x": 932,
      "y": 908
    },
    {
      "number_of_city": 8,
      "x": -674,
      "y": 661
    },
    {
      "number_of_city": 9,
      "x": 154,
      "y": 902
    },
    {
      "number_of_city": 10,
      "x": 381,
      "y": -98
    },
    {
      "number_of_city": 11,
      "x": -383,
      "y": -510
    },
    {
      "number_of_city": 12,
      "x": -251,
      "y": 992
    },
    {
      "number_of_city": 13,
      "x": 385,
      "y": 550
    },
    {
      "number_of_city": 14,
      "x": -697,
      "y": -411
    },
    {
      "number_of_city": 15,
      "x": 697,
      "y": -941
    },
    {
      "number_of_city": 16,
      "x": 816,
      "y": 389
    },
    {
      "number_of_city": 17,
      "x": -681,
      "y": 488
    },
    {
      "number_of_city": 18,
      "x": -757,
      "y": -826
    },
    {
      "number_of_city": 19,
      "x": -716,
      "y": -764
    },
    {
      "number_of_city": 20,
      "x": 169,
      "y": 996
    },
    {
      "number_of_city": 21,
      "x": -526,
      "y": 674
    },
    {
      "number_of_city": 22,
      "x": -357,
      "y": 330
    },
    {
      "number_of_city": 23,
      "x": 603,
      "y": -485
    },
    {
      "number_of_city": 24,
      "x": -112,
      "y": -44
    },
    {
      "number_of_city": 25,
      "x": 611,
      "y": -785
    },
    {
      "number_of_city": 26,
      "x": -188,
      "y": 905
    },
    {
      "number_of_city": 27,
      "x": 558,
      "y": 936
    },
    {
      "number_of_city": 28,
      "x": -130,
      "y": -158
    },
    {
      "number_of_city": 29,
      "x": 807,
      "y": -637
    },
    {
      "number_of_city": 30,
      "x": 456,
      "y": -397
    },
    {
      "number_of_city": 31,
      "x": -75,
      "y": 497
    },
    {
      "number_of_city": 32,
      "x": -859,
      "y": 113
    },
    {
      "number_of_city": 33,
      "x": 788,
      "y": -981
    },
    {
      "number_of_city": 34,
      "x": -501,
      "y": -567
    },
    {
      "number_of_city": 35,
      "x": -679,
      "y": -898
    },
    {
      "number_of_city": 36,
      "x": -561,
      "y": -962
    },
    {
      "number_of_city": 37,
      "x": -300,
      "y": 79
    },
    {
      "number_of_city": 38,
      "x": -261,
      "y": -749
    },
    {
      "number_of_city": 39,
      "x": 690,
      "y": -854
    },
    {
      "number_of_city": 40,
      "x": -109,
      "y": 681
    }
  ],
  "distance_matrix": {
    "0": {
      "40": 689.6680360869278
    },
    "1": {
      "40": 237.53947040439405
    },
    "2": {
      "40": 977.4712271980184
    },
    "3": {
      "40": 1114.0062836447557
    },
    "4": {
      "40": 1332.201186007579
    },
    "5": {
      "40": 659.1092473937837
    },
    "6": {
      "40": 1097.5481766191406
    },
    "7": {
      "40": 1065.4623409581402
    },
    "8": {
      "40": 565.3538714822779
    },
    "9": {
      "40": 343.5258360007293
    },
    "10": {
      "40": 920.2939747711054
    },
    "11": {
      "40": 1222.1116970228213
    },
    "12": {
      "40": 341.8844834150857
    },
    "13": {
      "40": 511.07435858199733
    },
    "14": {
      "40": 1240.2451370596057
    },
    "15": {
      "40": 1811.2205829219145
    },
    "16": {
      "40": 969.9943298803349
    },
    "17": {
      "40": 603.6828637620915
    },
    "18": {
      "40": 1640.4124481361387
    },
    "19": {
      "40": 1567.3142633179857
    },
    "20": {
      "40": 420.12974186553373
    },
    "21": {
      "40": 417.0587488591985
    },
    "22": {
      "40": 429.7731959999367
    },
    "23": {
      "40": 1366.1991070118586
    },
    "24": {
      "40": 725.0062068699826
    },
    "25": {
      "40": 1633.2654407658297
    },
    "26": {
      "40": 237.52263050075882
    },
    "27": {
      "40": 714.082628272107
    },
    "28": {
      "40": 839.2627717228972
    },
    "29": {
      "40": 1605.0482858780292
    },
    "30": {
      "40": 1217.0903828393355
    },
    "31": {
      "40": 187.11493793922494
    },
    "32": {
      "40": 940.8102890593831
    },
    "33": {
      "40": 1888.6113946495186
    },
    "34": {
      "40": 1308.1162027893392
    },
    "35": {
      "40": 1678.7319619284074
    },
    "36": {
      "40": 1704.0401990563485
    },
    "37": {
      "40": 631.5734319934619
    },
    "38": {
      "40": 1438.0556317472563
    },
    "39": {
      "40": 1730.4987720307693
    },
    "40": {
      "40": 0.0
    }
  },
  "stats": {
    "x": {
      "min": -859,
      "avg": 12.097560975609756,
      "stdev": 577.9370556071849,
      "median": -109.0,
      "q1": -501.0,
      "q3": 603.0,
      "max": 974
    },
    "y": {
      "min": -981,
      "avg": 0.4878048780487805,
      "stdev": 653.0916138625278,
      "median": -44.0,
      "q1": -567.0,
      "q3": 550.0,
      "max": 996
    }
  }
}