{
  "cities": [
    {
      "number_of_city": 0,
      "x": 0,
      "y": 0
    },
    {
      "number_of_city": 1,
      "x": -389,
      "y": -24
    },
    {
      "number_of_city": 2,
      "x": -330,
      "y": 393
    },
    {
      "number_of_city": 3,
      "x": 861,
      "y": -456
    },
    {
      "number_of_city": 4,
      "x": -476,
      "y": -890
    }
  ],
  "distance_matrix": {
    "0": {
      "4": 1009.2948033156616
    },
    "1": {
      "4": 870.3591212827037
    },
    "2": {
      "4": 1291.2803723436673
    },
    "3": {
      "4": 1405.675993961624
    },
    "4": {
      "4": 0.0
    }
  },
  "stats": {
    "x": {
      "min": -476,
      "avg": -66.8,
      "stdev": 549.0461729217316,
      "median": -330.0,
      "q1": -389.0,
      "q3": 0.0,
      "max": 861
    },
    "y": {
      "min": -890,
      "avg": -195.4,
      "stdev": 490.95702459583975,
      "median": -24.0,
      "q1": -456.0,
      "q3": 0.0,
      "max": 393
    }
  }
}