{"cities": [{"number_of_city": 0, "x": 0, "y": 0}, {"number_of_city": 1, "x": 30, "y": -983}, {"number_of_city": 2, "x": -36, "y": 56}, {"number_of_city": 3, "x": -742, "y": -533}, {"number_of_city": 4, "x": 685, "y": 551}, {"number_of_city": 5, "x": 193, "y": -968}, {"number_of_city": 6, "x": 34, "y": 400}, {"number_of_city": 7, "x": 907, "y": 572}], "distance_matrix": {"0": {"7": 1072.3026624978602}, "1": {"7": 1785.2602051241718}, "2": {"7": 1074.9441845975073}, "3": {"7": 1985.0002518891529}, "4": {"7": 222.9910312097776}, "5": {"7": 1697.4675254625638}, "6": {"7": 889.7825577072188}, "7": {"7": 0.0}}, "stats": {"x": {"min": -742, "avg": 133.875, "stdev": 498.52050753060445, "median": 32.0, "q1": -9.0, "q3": 316.0, "max": 907}, "y": {"min": -983, "avg": -113.125, "stdev": 641.3094723187194, "median": 28.0, "q1": -641.75, "q3": 437.75, "max": 572}}}