{
  "used_read_access_memory_in_bytes": [
    6996504576,
    6997934080,
    7004274688,
    7004155904,
    7004147712,
    7004266496,
    7004135424,
    7004205056,
    7004213248,
    7003742208,
    7004217344,
    7004098560,
    7004176384,
    7004135424,
    7004094464,
    7040487424,
    6616166400,
    6618349568,
    6619758592
  ],
  "utilization_of_cpu": [
    14.1,
    12.3,
    12.5,
    12.5,
    12.5,
    12.5,
    12.3,
    12.5,
    12.7,
    17.2,
    12.5,
    12.5,
    12.3,
    12.5,
    12.5,
    25.5,
    25.0,
    25.0,
    25.0
  ],
  "used_read_access_memory_in_percentage": [
    41.2,
    41.2,
    41.2,
    41.2,
    41.2,
    41.2,
    41.2,
    41.2,
    41.2,
    41.2,
    41.2,
    41.2,
    41.2,
    41.2,
    41.2,
    41.4,
    38.9,
    38.9,
    38.9
  ],
  "time_duration_with_cpu_profiler_in_sec": 20.9354733,
  "used_algorithm": "ant_colony_tsp_scikit_opt",
  "name_of_src_file": "TSP_CITIES_SET_55_N_5.json"
}