{
  "cities": [
    {
      "number_of_city": 0,
      "x": 0,
      "y": 0
    },
    {
      "number_of_city": 1,
      "x": 696,
      "y": -878
    },
    {
      "number_of_city": 2,
      "x": 379,
      "y": 201
    },
    {
      "number_of_city": 3,
      "x": 638,
      "y": -255
    },
    {
      "number_of_city": 4,
      "x": -333,
      "y": 324
    },
    {
      "number_of_city": 5,
      "x": 556,
      "y": 219
    },
    {
      "number_of_city": 6,
      "x": 306,
      "y": 598
    }
  ],
  "distance_matrix": {
    "0": {
      "6": 671.7439988567073
    },
    "1": {
      "6": 1526.6551673511606
    },
    "2": {
      "6": 403.655793963124
    },
    "3": {
      "6": 915.3321801400845
    },
    "4": {
      "6": 695.2675743913275
    },
    "5": {
      "6": 454.0275322048212
    },
    "6": {
      "6": 0.0
    }
  },
  "stats": {
    "x": {
      "min": -333,
      "avg": 320.2857142857143,
      "stdev": 372.08453980500826,
      "median": 379.0,
      "q1": 153.0,
      "q3": 597.0,
      "max": 696
    },
    "y": {
      "min": -878,
      "avg": 29.857142857142858,
      "stdev": 479.6892843537466,
      "median": 201.0,
      "q1": -127.5,
      "q3": 271.5,
      "max": 598
    }
  }
}