{
  "cities": [
    {
      "number_of_city": 0,
      "x": 0,
      "y": 0
    },
    {
      "number_of_city": 1,
      "x": -737,
      "y": 653
    },
    {
      "number_of_city": 2,
      "x": -735,
      "y": 623
    },
    {
      "number_of_city": 3,
      "x": 148,
      "y": 905
    },
    {
      "number_of_city": 4,
      "x": 925,
      "y": -342
    },
    {
      "number_of_city": 5,
      "x": -500,
      "y": 146
    },
    {
      "number_of_city": 6,
      "x": 309,
      "y": 948
    },
    {
      "number_of_city": 7,
      "x": -915,
      "y": -342
    },
    {
      "number_of_city": 8,
      "x": -882,
      "y": 712
    },
    {
      "number_of_city": 9,
      "x": -216,
      "y": 689
    },
    {
      "number_of_city": 10,
      "x": 258,
      "y": 424
    },
    {
      "number_of_city": 11,
      "x": 656,
      "y": 250
    },
    {
      "number_of_city": 12,
      "x": 40,
      "y": 637
    },
    {
      "number_of_city": 13,
      "x": 915,
      "y": -818
    },
    {
      "number_of_city": 14,
      "x": 696,
      "y": -348
    },
    {
      "number_of_city": 15,
      "x": 982,
      "y": 688
    },
    {
      "number_of_city": 16,
      "x": 515,
      "y": 551
    },
    {
      "number_of_city": 17,
      "x": -913,
      "y": -359
    },
    {
      "number_of_city": 18,
      "x": -647,
      "y": 639
    },
    {
      "number_of_city": 19,
      "x": -863,
      "y": 987
    },
    {
      "number_of_city": 20,
      "x": 612,
      "y": 132
    },
    {
      "number_of_city": 21,
      "x": 536,
      "y": 942
    },
    {
      "number_of_city": 22,
      "x": -807,
      "y": -695
    },
    {
      "number_of_city": 23,
      "x": -784,
      "y": 893
    },
    {
      "number_of_city": 24,
      "x": -821,
      "y": -822
    },
    {
      "number_of_city": 25,
      "x": -800,
      "y": -126
    },
    {
      "number_of_city": 26,
      "x": -90,
      "y": 855
    },
    {
      "number_of_city": 27,
      "x": -615,
      "y": 535
    },
    {
      "number_of_city": 28,
      "x": -532,
      "y": 884
    }
  ],
  "distance_matrix": {
    "0": {
      "28": 1031.7364004434467
    },
    "1": {
      "28": 308.8462400612965
    },
    "2": {
      "28": 330.65087327875
    },
    "3": {
      "28": 680.3241874283171
    },
    "4": {
      "28": 1904.1861778723214
    },
    "5": {
      "28": 738.6934411513345
    },
    "6": {
      "28": 843.4316806950045
    },
    "7": {
      "28": 1284.4317809833265
    },
    "8": {
      "28": 389.9794866400026
    },
    "9": {
      "28": 371.32330926027254
    },
    "10": {
      "28": 914.166286842826
    },
    "11": {
      "28": 1346.5882815471105
    },
    "12": {
      "28": 623.0513622487315
    },
    "13": {
      "28": 2233.9679943992037
    },
    "14": {
      "28": 1739.4849812516347
    },
    "15": {
      "28": 1526.6342063506897
    },
    "16": {
      "28": 1098.6801172315807
    },
    "17": {
      "28": 1300.0807667218219
    },
    "18": {
      "28": 270.64737205448716
    },
    "19": {
      "28": 346.6554485364394
    },
    "20": {
      "28": 1369.028852873452
    },
    "21": {
      "28": 1069.5737468730242
    },
    "22": {
      "28": 1602.7682302815963
    },
    "23": {
      "28": 252.1606630701942
    },
    "24": {
      "28": 1730.305464361712
    },
    "25": {
      "28": 1044.951673523709
    },
    "26": {
      "28": 442.9503358165563
    },
    "27": {
      "28": 358.73388465546435
    },
    "28": {
      "28": 0.0
    }
  },
  "stats": {
    "x": {
      "min": -915,
      "avg": -147.06896551724137,
      "stdev": 662.7521585369,
      "median": -216.0,
      "q1": -784.0,
      "q3": 515.0,
      "max": 982
    },
    "y": {
      "min": -822,
      "avg": 318.6551724137931,
      "stdev": 574.0395877253259,
      "median": 551.0,
      "q1": -126.0,
      "q3": 712.0,
      "max": 987
    }
  }
}