{
  "cities": [
    {
      "number_of_city": 0,
      "x": 0,
      "y": 0
    },
    {
      "number_of_city": 1,
      "x": 538,
      "y": 873
    },
    {
      "number_of_city": 2,
      "x": -596,
      "y": 416
    },
    {
      "number_of_city": 3,
      "x": 574,
      "y": -484
    },
    {
      "number_of_city": 4,
      "x": 145,
      "y": -198
    },
    {
      "number_of_city": 5,
      "x": 9,
      "y": -197
    },
    {
      "number_of_city": 6,
      "x": -443,
      "y": 477
    },
    {
      "number_of_city": 7,
      "x": 647,
      "y": 446
    },
    {
      "number_of_city": 8,
      "x": 65,
      "y": 822
    },
    {
      "number_of_city": 9,
      "x": 832,
      "y": 683
    },
    {
      "number_of_city": 10,
      "x": 753,
      "y": 467
    },
    {
      "number_of_city": 11,
      "x": -194,
      "y": 415
    },
    {
      "number_of_city": 12,
      "x": 859,
      "y": -17
    },
    {
      "number_of_city": 13,
      "x": 485,
      "y": 54
    },
    {
      "number_of_city": 14,
      "x": 250,
      "y": -967
    },
    {
      "number_of_city": 15,
      "x": 71,
      "y": -968
    },
    {
      "number_of_city": 16,
      "x": 447,
      "y": 376
    },
    {
      "number_of_city": 17,
      "x": 35,
      "y": -23
    },
    {
      "number_of_city": 18,
      "x": -882,
      "y": 199
    },
    {
      "number_of_city": 19,
      "x": -467,
      "y": -897
    },
    {
      "number_of_city": 20,
      "x": -989,
      "y": -825
    },
    {
      "number_of_city": 21,
      "x": 943,
      "y": 458
    },
    {
      "number_of_city": 22,
      "x": 902,
      "y": 649
    },
    {
      "number_of_city": 23,
      "x": 638,
      "y": 387
    },
    {
      "number_of_city": 24,
      "x": -788,
      "y": 296
    },
    {
      "number_of_city": 25,
      "x": -517,
      "y": -177
    },
    {
      "number_of_city": 26,
      "x": 819,
      "y": 286
    },
    {
      "number_of_city": 27,
      "x": 206,
      "y": 826
    },
    {
      "number_of_city": 28,
      "x": 128,
      "y": 279
    },
    {
      "number_of_city": 29,
      "x": 829,
      "y": -990
    },
    {
      "number_of_city": 30,
      "x": -526,
      "y": -712
    },
    {
      "number_of_city": 31,
      "x": -858,
      "y": -613
    },
    {
      "number_of_city": 32,
      "x": 225,
      "y": 702
    },
    {
      "number_of_city": 33,
      "x": -180,
      "y": 77
    },
    {
      "number_of_city": 34,
      "x": -514,
      "y": -547
    },
    {
      "number_of_city": 35,
      "x": 592,
      "y": 167
    },
    {
      "number_of_city": 36,
      "x": -287,
      "y": 438
    },
    {
      "number_of_city": 37,
      "x": -647,
      "y": -277
    },
    {
      "number_of_city": 38,
      "x": 40,
      "y": -638
    },
    {
      "number_of_city": 39,
      "x": 334,
      "y": 262
    },
    {
      "number_of_city": 40,
      "x": 546,
      "y": -511
    },
    {
      "number_of_city": 41,
      "x": 574,
      "y": -328
    },
    {
      "number_of_city": 42,
      "x": -725,
      "y": -467
    },
    {
      "number_of_city": 43,
      "x": 898,
      "y": 727
    }
  ],
  "distance_matrix": {
    "0": {
      "43": 1155.3930067297447
    },
    "1": {
      "43": 388.47908566613984
    },
    "2": {
      "43": 1526.0265397430019
    },
    "3": {
      "43": 1253.5936343169583
    },
    "4": {
      "43": 1192.7422185870676
    },
    "5": {
      "43": 1282.223459464067
    },
    "6": {
      "43": 1364.1044681401788
    },
    "7": {
      "43": 376.7784494898826
    },
    "8": {
      "43": 838.3996660304679
    },
    "9": {
      "43": 79.32212806020776
    },
    "10": {
      "43": 297.6995129320839
    },
    "11": {
      "43": 1135.6971427277608
    },
    "12": {
      "43": 745.0214762005187
    },
    "13": {
      "43": 789.6188954172766
    },
    "14": {
      "43": 1813.7089071843916
    },
    "15": {
      "43": 1885.9888652905668
    },
    "16": {
      "43": 571.4910323005953
    },
    "17": {
      "43": 1143.358648893688
    },
    "18": {
      "43": 1856.6593656349567
    },
    "19": {
      "43": 2121.461995888684
    },
    "20": {
      "43": 2443.2504988232376
    },
    "21": {
      "43": 272.7379694871985
    },
    "22": {
      "43": 78.10249675906654
    },
    "23": {
      "43": 428.01869118065395
    },
    "24": {
      "43": 1740.2175151399897
    },
    "25": {
      "43": 1679.119114297732
    },
    "26": {
      "43": 448.02008883531107
    },
    "27": {
      "43": 699.0457781862358
    },
    "28": {
      "43": 890.8445431162498
    },
    "29": {
      "43": 1718.3858705191917
    },
    "30": {
      "43": 2024.474499715914
    },
    "31": {
      "43": 2208.876637569423
    },
    "32": {
      "43": 673.4641787058907
    },
    "33": {
      "43": 1258.8026056534836
    },
    "34": {
      "43": 1901.7938899891335
    },
    "35": {
      "43": 638.1504524796641
    },
    "36": {
      "43": 1219.731937763376
    },
    "37": {
      "43": 1842.563703104997
    },
    "38": {
      "43": 1612.2620754703623
    },
    "39": {
      "43": 730.9726397068498
    },
    "40": {
      "43": 1287.0695396908436
    },
    "41": {
      "43": 1103.6308259558539
    },
    "42": {
      "43": 2014.88585284626
    },
    "43": {
      "43": 0.0
    }
  },
  "stats": {
    "x": {
      "min": -989,
      "avg": 108.43181818181819,
      "stdev": 576.85822681815,
      "median": 136.5,
      "q1": -449.0,
      "q3": 578.5,
      "max": 943
    },
    "y": {
      "min": -990,
      "avg": 21.5,
      "stdev": 550.2203575481964,
      "median": 122.0,
      "q1": -471.25,
      "q3": 440.0,
      "max": 873
    }
  }
}