{
  "cities": [
    {
      "number_of_city": 0,
      "x": 0,
      "y": 0
    },
    {
      "number_of_city": 1,
      "x": 120,
      "y": 282
    },
    {
      "number_of_city": 2,
      "x": 352,
      "y": -91
    },
    {
      "number_of_city": 3,
      "x": 30,
      "y": -606
    },
    {
      "number_of_city": 4,
      "x": 766,
      "y": 527
    },
    {
      "number_of_city": 5,
      "x": -265,
      "y": 767
    },
    {
      "number_of_city": 6,
      "x": -190,
      "y": -893
    },
    {
      "number_of_city": 7,
      "x": -534,
      "y": -486
    },
    {
      "number_of_city": 8,
      "x": 780,
      "y": 724
    },
    {
      "number_of_city": 9,
      "x": 656,
      "y": -914
    },
    {
      "number_of_city": 10,
      "x": 436,
      "y": 64
    },
    {
      "number_of_city": 11,
      "x": 619,
      "y": 922
    },
    {
      "number_of_city": 12,
      "x": 318,
      "y": 680
    },
    {
      "number_of_city": 13,
      "x": 603,
      "y": 608
    },
    {
      "number_of_city": 14,
      "x": 952,
      "y": 225
    },
    {
      "number_of_city": 15,
      "x": 769,
      "y": 913
    },
    {
      "number_of_city": 16,
      "x": -534,
      "y": 271
    },
    {
      "number_of_city": 17,
      "x": 167,
      "y": -903
    },
    {
      "number_of_city": 18,
      "x": -16,
      "y": 538
    }
  ],
  "distance_matrix": {
    "0": {
      "18": 538.2378656319156
    },
    "1": {
      "18": 289.882734911895
    },
    "2": {
      "18": 728.7420668521888
    },
    "3": {
      "18": 1144.9244516560907
    },
    "4": {
      "18": 782.0773619022609
    },
    "5": {
      "18": 338.2927726097618
    },
    "6": {
      "18": 1441.5398017397924
    },
    "7": {
      "18": 1147.5626344561765
    },
    "8": {
      "18": 817.4423527075166
    },
    "9": {
      "18": 1599.964999617179
    },
    "10": {
      "18": 654.9656479541503
    },
    "11": {
      "18": 742.0788367821845
    },
    "12": {
      "18": 362.93250061133955
    },
    "13": {
      "18": 622.9454229705841
    },
    "14": {
      "18": 1017.346057150663
    },
    "15": {
      "18": 869.9712638932392
    },
    "16": {
      "18": 582.7632452377209
    },
    "17": {
      "18": 1452.5735781708272
    },
    "18": {
      "18": 0.0
    }
  },
  "stats": {
    "x": {
      "min": -534,
      "avg": 264.6842105263158,
      "stdev": 451.7887968498825,
      "median": 318.0,
      "q1": -8.0,
      "q3": 637.5,
      "max": 952
    },
    "y": {
      "min": -914,
      "avg": 138.31578947368422,
      "stdev": 628.0266318337127,
      "median": 271.0,
      "q1": -288.5,
      "q3": 644.0,
      "max": 922
    }
  }
}